{
    "url": "https://asia.pokemon-card.com/tw/card-search/detail/858/",
    "name": "鋁鋼龍V",
    "img": "https://asia.pokemon-card.com/tw/card-img/tw00000858.png",
    "card_type": "Pokémon",
    "lang": "tc",
    "tags": [
        "V"
    ],
    "regulation": "E",
    "set_name": "S7D",
    "set_img": "https://asia.pokemon-card.com/tw/card-img/mark/S_mark_expantion_S7D_F_OL.png",
    "set_full_name": "擴充包「摩天巔峰」",
    "number": "048",
    "set_total": "067",
    "author": [
        "PLANETA Mochizuki"
    ],
    "pokedex_number": "884",
    "pokemon_category": "",
    "stage": "基礎",
    "hp": "220",
    "types": [
        "Dragon"
    ],
    "attacks": [
        {
            "cost": [
                "Fighting",
                "Metal"
            ],
            "name": "金屬爪",
            "damage": "70",
            "effect": ""
        },
        {
            "cost": [
                "Fighting",
                "Metal",
                "Metal"
            ],
            "name": "廣域破壞",
            "damage": "140",
            "effect": "在下個對手的回合，受到這個招式的寶可夢使用招式的傷害「-30」點。"
        }
    ],
    "rule_box": "寶可夢【V】【氣絕】時，對手獲得2張獎賞卡。",
    "weakness": {
        "type": [],
        "value": null
    },
    "resistance": {
        "type": [],
        "value": null
    },
    "retreat": 2
}