{
    "url": "https://pkmncards.com/card/bea-vivid-voltage-viv-147/",
    "name": "Bea",
    "img": "https://pkmncards.com/wp-content/uploads/en_US-SWSH4-147-bea.jpg",
    "card_type": "Supporter",
    "regulation": "D",
    "set_name": "VIV",
    "set_img": null,
    "series": "Sword & Shield",
    "set_full_name": "Vivid Voltage",
    "set_code": "SWSH4",
    "date": "Nov 13, 2020",
    "number": "147",
    "set_total": "185",
    "rarity": "Uncommon",
    "rarity_img": null,
    "effect": "Discard the top 5 cards of your deck, and attach any Energy cards you discarded in this way to your Benched {F} Pokémon in any way you like.",
    "author": [
        "take"
    ]
}