{
    "url": "https://pocket.limitlesstcg.com/cards/A2/55",
    "name": "Electrode",
    "img": "https://limitlesstcg.nyc3.cdn.digitaloceanspaces.com/pocket/A2/A2_055_EN.webp",
    "card_type": "Pokémon",
    "game": "TCG Pocket",
    "set_name": "Space-Time Smackdown",
    "set_img": "https://s3.limitlesstcg.com/pocket/sets/A2.webp",
    "number": "55",
    "set_total": 207,
    "rarity": "2 diamond",
    "author": "Anesaki Dynamic",
    "stage": "Stage 1",
    "hp": 80,
    "types": [
        "Lightning"
    ],
    "attacks": [
        {
            "cost": [
                "Lightning"
            ],
            "name": "Rolling Attack",
            "damage": "50",
            "effect": ""
        }
    ],
    "weakness": {
        "type": [
            "Fighting"
        ],
        "value": "+20"
    },
    "retreat": 1,
    "evolve_from": "Voltorb"
}