{
    "url": "https://asia.pokemon-card.com/tw/card-search/detail/12783/",
    "name": "<火箭隊的>閃電鳥",
    "img": "https://asia.pokemon-card.com/tw/card-img/tw00012783.png",
    "card_type": "Pokémon",
    "lang": "tc",
    "regulation": "I",
    "set_name": "SV10",
    "set_img": "https://asia.pokemon-card.com/tw/card-img/mark/twhk_exp_SV10.png",
    "set_full_name": "擴充包「火箭隊的榮耀」",
    "number": "033",
    "set_total": "098",
    "author": [
        "Nurikabe"
    ],
    "pokedex_number": "145",
    "pokemon_category": "電擊寶可夢",
    "height": "1.6m",
    "weight": "52.6kg",
    "flavor_text": "傳說的鳥寶可夢。據說只要牠磨蹭翅膀，立刻就會有雷電劈下。",
    "stage": "基礎",
    "hp": "120",
    "types": [
        "Lightning"
    ],
    "attacks": [
        {
            "cost": [
                "Colorless",
                "Colorless"
            ],
            "name": "阻礙之翼",
            "damage": "30",
            "effect": "若希望，選擇1個對手的戰鬥寶可夢身上附加的能量，改附於對手的備戰寶可夢身上。"
        },
        {
            "cost": [
                "Lightning",
                "Colorless",
                "Colorless"
            ],
            "name": "惡棍閃電",
            "damage": "60+",
            "effect": "若這隻寶可夢身上附有「火箭隊能量」，則增加60點傷害。"
        }
    ],
    "weakness": {
        "type": [
            "Lightning"
        ],
        "value": "×2"
    },
    "resistance": {
        "type": [
            "Fighting"
        ],
        "value": "-30"
    },
    "retreat": 1
}