{
    "url": "https://pkmncards.com/card/perrin-twilight-masquerade-twm-160/",
    "name": "Perrin",
    "img": "https://pkmncards.com/wp-content/uploads/sv6_en_160_std.jpg",
    "card_type": "Supporter",
    "regulation": "H",
    "set_name": "TWM",
    "set_img": null,
    "series": "Scarlet & Violet",
    "set_full_name": "Twilight Masquerade",
    "set_code": "sv6",
    "date": "May 24, 2024",
    "number": "160",
    "set_total": "167",
    "rarity": "Uncommon",
    "rarity_img": null,
    "effect": "Reveal up to 2 Pokémon in your hand and put them into your deck. If you do, search your deck for up to that many Pokémon, reveal them, and put them into your hand. Then, shuffle your deck.",
    "author": [
        "Naoki Saito"
    ]
}