{
    "jp_id": 23561,
    "url": "https://www.pokemon-card.com/card-search/details.php/card/23561",
    "name": "ミュウツー",
    "img": "https://www.pokemon-card.com/assets/images/card_images/large/CPm/023561_P_MYUUTSU.gif",
    "card_type": "Pokémon",
    "tags": [
        "レベルアップ"
    ],
    "set_name": "CPm",
    "set_img": "https://www.pokemon-card.com/assets/images/card/regulation_logo_1/CPm.gif",
    "number": "006",
    "set_total": "012",
    "author": [
        "Shizurow"
    ],
    "stage": "レベルアップ",
    "level": "X",
    "hp": 120,
    "types": [
        "Psychic"
    ],
    "poke_body": {
        "name": "サイコバリア",
        "effect": "このポケモンは、相手の「進化していないポケモン」のワザによるダメージや効果を受けない。"
    },
    "attacks": [
        {
            "cost": [
                "Psychic",
                "Psychic",
                "Colorless"
            ],
            "name": "ギガバーン",
            "damage": {
                "amount": 120,
                "suffix": ""
            },
            "effect": "自分のエネルギーをすべてトラッシュ。"
        }
    ],
    "rule_box": "このカードは、バトル場のミュウツーに重ねてレベルアップさせる。\nレベルアップ前のワザ・ポケパワーも使うことができ、ポケボディーもはたらく。",
    "weakness": {
        "type": [
            "Psychic"
        ],
        "value": "×2"
    },
    "resistance": {
        "type": [],
        "value": null
    },
    "retreat": 2,
    "sources": [
        {
            "name": "ポケモンカードゲーム　コレクションパック　ミュウツーLV.X",
            "link": null
        }
    ]
}