{
    "jp_id": 42131,
    "url": "https://www.pokemon-card.com/card-search/details.php/card/42131",
    "name": "\u30b7\u30f3\u30dc\u30e9\u30fc",
    "img": "https://www.pokemon-card.com/assets/images/card_images/large/S12/042131_P_SHINBORA.jpg",
    "card_type": "Pok\u00e9mon",
    "set_name": "S12",
    "set_img": "https://www.pokemon-card.com/assets/images/card/regulation_logo_1/S12.gif",
    "number": "039",
    "set_total": "098",
    "rarity": "rare_c_c",
    "rarity_img": "https://www.pokemon-card.com/assets/images/card/rarity/ic_rare_c_c.gif",
    "author": [
        "Yuya Oka"
    ],
    "pokedex_number": 561,
    "pokemon_category": "\u3068\u308a\u3082\u3069\u304d\u30dd\u30b1\u30e2\u30f3",
    "height": "1.4 m",
    "weight": "14.0 kg",
    "flavor_text": "\u30b5\u30a4\u30b3\u30d1\u30ef\u30fc\u3067 \u7a7a\u3092 \u98db\u3076\u3002 \u53e4\u4ee3\u90fd\u5e02\u306e \u5b88\u308a\u795e \u3068\u3082 \u305d\u306e\u9063\u3044\u3068\u3082 \u3044\u308f\u308c\u3066\u3044\u308b\u3002",
    "stage": "\u305f\u306d",
    "hp": 100,
    "types": [
        "Psychic"
    ],
    "attacks": [
        {
            "cost": [
                "Colorless"
            ],
            "name": "\u30ef\u30fc\u30cb\u30f3\u30b0",
            "damage": null,
            "effect": "\u81ea\u5206\u306e\u5c71\u672d\u304b\u3089\u305f\u306d\u30dd\u30b1\u30e2\u30f3\u30921\u679a\u9078\u3073\u3001\u30d9\u30f3\u30c1\u306b\u51fa\u3059\u3002\u305d\u3057\u3066\u5c71\u672d\u3092\u5207\u308b\u3002\u76f8\u624b\u306e\u30d0\u30c8\u30eb\u30dd\u30b1\u30e2\u30f3\u304c\u300c\u30dd\u30b1\u30e2\u30f3V\u300d\u306a\u3089\u3001\u30d9\u30f3\u30c1\u306b\u51fa\u305b\u308b\u305f\u306d\u30dd\u30b1\u30e2\u30f3\u306e\u6570\u306f5\u679a\u307e\u3067\u306b\u306a\u308b\u3002"
        },
        {
            "cost": [
                "Psychic",
                "Colorless",
                "Colorless"
            ],
            "name": "\u30ab\u30c3\u30bf\u30fc\u30a6\u30a4\u30f3\u30c9",
            "damage": {
                "amount": 70,
                "prefix": "",
                "suffix": ""
            },
            "effect": ""
        }
    ],
    "weakness": {
        "type": [
            "Electric"
        ],
        "value": "\u00d72"
    },
    "resistance": {
        "type": [
            "Fighting"
        ],
        "value": "\uff0d30"
    },
    "retreat": 1,
    "sources": [
        {
            "name": "\u62e1\u5f35\u30d1\u30c3\u30af\u300c\u30d1\u30e9\u30c0\u30a4\u30e0\u30c8\u30ea\u30ac\u30fc\u300d",
            "link": "https://www.pokemon-card.com/ex/s12/index.html"
        }
    ]
}