{
    "url": "https://pkmncards.com/card/swalot-hidden-legends-hl-50/",
    "name": "Swalot",
    "img": "https://pkmncards.com/wp-content/uploads/swalot-hidden-legends-hl-50.jpg",
    "card_type": "Pokémon",
    "set_name": "HL",
    "series": "EX",
    "set_full_name": "Hidden Legends",
    "set_code": "EX5",
    "date": "Jun 14, 2004",
    "number": "50",
    "set_total": "101",
    "rarity": "Uncommon",
    "author": [
        "Yuka Morii"
    ],
    "stage": "Stage 1",
    "hp": 80,
    "types": [
        "Grass"
    ],
    "attacks": [
        {
            "cost": [
                "Colorless"
            ],
            "name": "Amnesia",
            "damage": {
                "amount": 10,
                "suffix": ""
            },
            "effect": "Choose 1 of the Defending Pokémon’s attacks. That Pokémon can’t use that attack during your opponent’s next turn."
        },
        {
            "cost": [
                "Grass",
                "Colorless",
                "Colorless"
            ],
            "name": "Swallow Up",
            "damage": {
                "amount": 50,
                "suffix": "+"
            },
            "effect": "Before doing damage, count the remaining HP of the Defending Pokémon and Swalot. If the Defending Pokémon has fewer remaining HP than Swalot’s, this attack does 50 damage plus 30 more damage."
        }
    ],
    "weakness": {
        "type": [
            "Psychic"
        ],
        "value": "×2"
    },
    "resistance": {
        "type": [],
        "value": null
    },
    "retreat": 2,
    "evolve_from": "Gulpin"
}