{
    "jp_id": 40462,
    "url": "https://www.pokemon-card.com/card-search/details.php/card/40462",
    "name": "クラッシュハンマー",
    "img": "https://www.pokemon-card.com/assets/images/card_images/large/SI/040462_T_KURASSHIXYUHANMA.jpg",
    "card_type": "グッズ",
    "set_name": "SI",
    "set_img": "https://www.pokemon-card.com/assets/images/card/regulation_logo_1/SI.gif",
    "number": "372",
    "set_total": "414",
    "effect": "コインを1回投げオモテなら、相手の場のポケモンについているエネルギーを1個選び、トラッシュする。",
    "author": [
        "sadaji"
    ],
    "sources": [
        {
            "name": "スタートデッキ100",
            "link": "https://www.pokemon-card.com/ex/si/"
        }
    ]
}