{
    "url": "https://asia.pokemon-card.com/tw/card-search/detail/10477/",
    "name": "晶光花",
    "img": "https://asia.pokemon-card.com/tw/card-img/tw00010477.png",
    "card_type": "Pokémon",
    "lang": "tc",
    "regulation": "H",
    "set_name": "SV6",
    "set_img": "https://asia.pokemon-card.com/tw/card-img/mark/sv6_F.png",
    "set_full_name": "擴充包「變幻假面」",
    "number": "063",
    "set_total": "101",
    "author": [
        "Kazumasa Yasukuni"
    ],
    "pokedex_number": "970",
    "pokemon_category": "礦石寶可夢",
    "height": "1.5m",
    "weight": "45.0kg",
    "flavor_text": "最近發現牠的毒能量 結晶化後所形成的花瓣 與太晶的寶石類似。",
    "stage": "1階進化",
    "hp": "130",
    "types": [
        "Fighting"
    ],
    "attacks": [
        {
            "cost": [
                "Colorless"
            ],
            "name": "神經毒",
            "damage": "",
            "effect": "擲1次硬幣若為正面，則將對手的戰鬥寶可夢【中毒】與【麻痺】。"
        },
        {
            "cost": [
                "Fighting"
            ],
            "name": "毒液衝擊",
            "damage": "30+",
            "effect": "若對手的戰鬥寶可夢【中毒】，則增加100點傷害。"
        }
    ],
    "weakness": {
        "type": [
            "Grass"
        ],
        "value": "×2"
    },
    "resistance": {
        "type": [],
        "value": null
    },
    "retreat": 3,
    "evolve_from": [
        "晶光芽"
    ]
}