{
    "url": "https://pkmncards.com/card/wigglytuff-firered-leafgreen-rg-52/",
    "name": "Wigglytuff",
    "img": "https://pkmncards.com/wp-content/uploads/en_US-EX06-052-wigglytuff.jpg",
    "card_type": "Pokémon",
    "set_name": "RG",
    "series": "EX",
    "set_full_name": "FireRed & LeafGreen",
    "set_code": "EX6",
    "date": "Aug 30, 2004",
    "number": "52",
    "set_total": "112",
    "rarity": "Uncommon",
    "author": [
        "Kyoko Umemoto"
    ],
    "stage": "Stage 1",
    "hp": 80,
    "types": [
        "Colorless"
    ],
    "poke_power": {
        "name": "Assistance",
        "effect": "Once during your turn (before your attack), if Wigglytuff is on your Bench, you may choose 1 of your Active Pokémon and remove 1 Special Condition from it."
    },
    "attacks": [
        {
            "cost": [
                "Colorless",
                "Colorless"
            ],
            "name": "Expand",
            "damage": {
                "amount": 30,
                "suffix": ""
            },
            "effect": "During your opponent’s next turn, any damage done to Wigglytuff by attacks is reduced by 10 (after applying Weakness and Resistance)."
        }
    ],
    "weakness": {
        "type": [
            "Fighting"
        ],
        "value": "×2"
    },
    "resistance": {
        "type": [],
        "value": null
    },
    "retreat": 1,
    "evolve_from": "Jigglypuff"
}