{
    "jp_id": 34452,
    "url": "https://www.pokemon-card.com/card-search/details.php/card/34452",
    "name": "ポッチャマ",
    "img": "https://www.pokemon-card.com/assets/images/card_images/large/SM5M/034452_P_POCCHAMA.jpg",
    "card_type": "Pokémon",
    "set_name": "SM5M",
    "set_img": "https://www.pokemon-card.com/assets/images/card/regulation_logo_1/SM5M.gif",
    "number": "004",
    "set_total": "066",
    "rarity": "rare_c_c",
    "rarity_img": "https://www.pokemon-card.com/assets/images/card/rarity/ic_rare_c_c.gif",
    "author": [
        "Shibuzoh."
    ],
    "pokedex_number": 393,
    "pokemon_category": "ペンギンポケモン",
    "height": "0.4 m",
    "weight": "5.2 kg",
    "flavor_text": "プライドが 高く 人から 食べ物を もらう ことを 嫌う。 長い 産毛が 寒さを 防ぐ。",
    "stage": "たね",
    "hp": 70,
    "types": [
        "Water"
    ],
    "attacks": [
        {
            "cost": [
                "Colorless"
            ],
            "name": "つつく",
            "damage": {
                "amount": 10,
                "suffix": ""
            },
            "effect": ""
        },
        {
            "cost": [
                "Water",
                "Colorless"
            ],
            "name": "スプラッシュ",
            "damage": {
                "amount": 20,
                "suffix": ""
            },
            "effect": ""
        }
    ],
    "weakness": {
        "type": [
            "Electric"
        ],
        "value": "×2"
    },
    "resistance": {
        "type": [],
        "value": null
    },
    "retreat": 1,
    "sources": [
        {
            "name": "拡張パック「ウルトラムーン」",
            "link": "https://www.pokemon-card.com/products/sm/sm5.html"
        },
        {
            "name": "ポケモンセンターオンラインでの購入はこちら",
            "link": "https://www.pokemon-card.comhttps://www.pokemoncenter-online.com/?p_cd=4521329191782"
        }
    ]
}