{
    "url": "https://pkmncards.com/card/swampert-supreme-victors-sv-12/",
    "name": "Swampert",
    "img": "https://pkmncards.com/wp-content/uploads/swampert-supreme-victors-sv-12.jpg",
    "card_type": "Pokémon",
    "set_name": "SV",
    "series": "Platinum",
    "set_full_name": "Supreme Victors",
    "set_code": "PL3",
    "date": "Aug 19, 2009",
    "number": "12",
    "set_total": "147",
    "rarity": "Rare Holo",
    "author": [
        "Kagemaru Himeno"
    ],
    "stage": "Stage 2",
    "level": "60",
    "hp": 130,
    "types": [
        "Water"
    ],
    "poke_body": {
        "name": "Root Protector",
        "effect": "Any damage done to Swampert by attacks from your opponent’s Pokémon that isn’t an Evolved Pokémon is reduced by 20 (after applying Weakness and Resistance)."
    },
    "attacks": [
        {
            "cost": [
                "Water",
                "Colorless",
                "Colorless"
            ],
            "name": "Drag Off",
            "damage": {
                "amount": 30,
                "suffix": ""
            },
            "effect": "Before doing damage, you may switch your opponent’s Active Pokémon with 1 of his or her Benched Pokémon."
        },
        {
            "cost": [
                "Water",
                "Colorless",
                "Colorless",
                "Colorless"
            ],
            "name": "Push Over",
            "damage": {
                "amount": 60,
                "suffix": "+"
            },
            "effect": "Does 60 damage plus 10 more damage for each {F} Energy attached to Swampert."
        }
    ],
    "weakness": {
        "type": [
            "Grass"
        ],
        "value": "+30"
    },
    "resistance": {
        "type": [],
        "value": null
    },
    "retreat": 2,
    "evolve_from": "Marshtomp"
}