{
    "url": "https://pkmncards.com/card/silcoon-platinum-pl-63/",
    "name": "Silcoon",
    "img": "https://pkmncards.com/wp-content/uploads/silcoon-platinum-pl-63.jpg",
    "card_type": "Pokémon",
    "set_name": "PL",
    "series": "Platinum",
    "set_full_name": "Platinum",
    "set_code": "PL1",
    "date": "Feb 11, 2009",
    "number": "63",
    "set_total": "127",
    "rarity": "Uncommon",
    "author": [
        "Kyoko Umemoto"
    ],
    "flavor_text": "It wraps silk around the branches of a tree. It drinks rainwater on its silk while awaiting evolution.",
    "stage": "Stage 1",
    "level": "10",
    "hp": 80,
    "types": [
        "Grass"
    ],
    "attacks": [
        {
            "cost": [
                "No Energy Cost"
            ],
            "name": "Ascension",
            "damage": null,
            "effect": "Search your deck for a card that evolves from Silcoon and put it onto Silcoon. (This counts as evolving Silcoon.) Shuffle your deck afterward."
        },
        {
            "cost": [
                "Grass",
                "Colorless"
            ],
            "name": "Sticky String",
            "damage": {
                "amount": 20,
                "suffix": ""
            },
            "effect": "Flip a coin. If heads, the Defending Pokémon is now Paralyzed."
        }
    ],
    "weakness": {
        "type": [
            "Fire"
        ],
        "value": "+20"
    },
    "resistance": {
        "type": [],
        "value": null
    },
    "retreat": 2,
    "evolve_from": "Wurmple"
}