{
    "jp_id": 26007,
    "url": "https://www.pokemon-card.com/card-search/details.php/card/26007",
    "name": "モジャンボ",
    "img": "https://www.pokemon-card.com/assets/images/card_images/large/LL/026007_P_MOJANBO.jpg",
    "card_type": "Pokémon",
    "set_name": "LL",
    "set_img": "https://www.pokemon-card.com/assets/images/card/regulation_logo_1/LL.gif",
    "number": "004",
    "set_total": "040",
    "rarity": "rare_u",
    "rarity_img": "https://www.pokemon-card.com/assets/images/card/rarity/ic_rare_u.gif",
    "author": [
        "Hideaki Hakozaki"
    ],
    "pokedex_number": 465,
    "pokemon_category": "ツルじょうポケモン",
    "height": "2.0 m",
    "weight": "128.6 kg",
    "stage": "1 進化",
    "hp": 110,
    "types": [
        "Grass"
    ],
    "attacks": [
        {
            "cost": [
                "Colorless"
            ],
            "name": "おしつぶす",
            "damage": {
                "amount": 20,
                "suffix": "×"
            },
            "effect": "このポケモンについているエネルギーの数×20ダメージ。"
        },
        {
            "cost": [
                "Grass",
                "Colorless",
                "Colorless"
            ],
            "name": "しばきたおす",
            "damage": {
                "amount": 30,
                "suffix": ""
            },
            "effect": "コインを1回投げオモテなら、相手のバトルポケモンをマヒにする。ウラなら、相手のバトルポケモンについているエネルギーを1個、ロストゾーンにおく。"
        }
    ],
    "weakness": {
        "type": [
            "Fire"
        ],
        "value": "×2"
    },
    "resistance": {
        "type": [
            "Water"
        ],
        "value": "－20"
    },
    "retreat": 4,
    "evolve_from": "モンジャラ",
    "sources": [
        {
            "name": "ポケモンカードゲーム 強化パック「ロストリンク」",
            "link": null
        }
    ]
}