{
    "jp_id": 34180,
    "url": "https://www.pokemon-card.com/card-search/details.php/card/34180",
    "name": "キテルグマ",
    "img": "https://www.pokemon-card.com/assets/images/card_images/large/SMP/034180_P_KITERUGUMA.jpg",
    "card_type": "Pokémon",
    "set_name": "SMP",
    "set_img": "https://www.pokemon-card.com/assets/images/card/regulation_logo_1/SMP.gif",
    "number": "087",
    "set_total": "SM-P",
    "author": [
        "Mitsuhiro Arita"
    ],
    "pokedex_number": 760,
    "pokemon_category": "ごうわんポケモン",
    "height": "2.1 m",
    "weight": "135.0 kg",
    "flavor_text": "圧倒的な 筋力を 持つ 非常に 危険な ポケモン。 生息地は 基本 立ち入り禁止。",
    "stage": "1 進化",
    "hp": 120,
    "types": [
        "Colorless"
    ],
    "attacks": [
        {
            "cost": [
                "Colorless",
                "Colorless"
            ],
            "name": "かきみだす",
            "damage": null,
            "effect": "コインを1回投げオモテなら、相手の山札を上から3枚トラッシュする。"
        },
        {
            "cost": [
                "Colorless",
                "Colorless",
                "Colorless"
            ],
            "name": "あばれまわる",
            "damage": {
                "amount": 120,
                "suffix": ""
            },
            "effect": "このポケモンをこんらんにする。"
        }
    ],
    "weakness": {
        "type": [
            "Fighting"
        ],
        "value": "×2"
    },
    "resistance": {
        "type": [],
        "value": null
    },
    "retreat": 2,
    "evolve_from": "ヌイコグマ",
    "sources": [
        {
            "name": "月刊コロコロイチバン！　2017年7月号付録",
            "link": "https://www.pokemon-card.com/card-search/index.php?regulation_detail=all&pg=10582"
        }
    ]
}