{
    "url": "https://pkmncards.com/card/magikarp-team-rocket-ro-47/",
    "name": "Magikarp",
    "img": "https://pkmncards.com/wp-content/uploads/magikarp-team-rocket-tr-47.jpg",
    "card_type": "Pokémon",
    "set_name": "RO",
    "series": "Classic",
    "set_full_name": "Team Rocket",
    "set_code": "RO",
    "date": "Apr 24, 2000",
    "number": "47",
    "set_total": "82",
    "rarity": "Uncommon",
    "author": [
        "Kagemaru Himeno"
    ],
    "flavor_text": "Recent research has revealed the presence of dragon DNA in this species of Pokémon.",
    "stage": "Basic",
    "level": "6",
    "hp": 30,
    "types": [
        "Water"
    ],
    "attacks": [
        {
            "cost": [
                "Colorless"
            ],
            "name": "Flop",
            "damage": {
                "amount": 10,
                "suffix": ""
            },
            "effect": null
        },
        {
            "cost": [
                "Water",
                "Water",
                "Water"
            ],
            "name": "Rapid Evolution",
            "damage": null,
            "effect": "Search your deck for an Evolution card named Gyarados or Dark Gyarados and put it on Magikarp. (This counts as evolving Magikarp.) Shuffle your deck afterward."
        }
    ],
    "weakness": {
        "type": [
            "Lightning"
        ],
        "value": "×2"
    },
    "resistance": {
        "type": [],
        "value": null
    },
    "retreat": 1
}