{
    "url": "https://pkmncards.com/card/snorlax-dragon-frontiers-df-10/",
    "name": "Snorlax",
    "img": "https://pkmncards.com/wp-content/uploads/snorlax-delta-dragon-frontiers-df-10.jpg",
    "card_type": "Pokémon",
    "set_name": "DF",
    "series": "EX",
    "set_full_name": "Dragon Frontiers",
    "set_code": "EX15",
    "date": "Nov 8, 2006",
    "number": "10",
    "set_total": "101",
    "rarity": "Rare Holo",
    "author": [
        "Masakazu Fukuda"
    ],
    "stage": "Basic",
    "hp": 80,
    "types": [
        "Grass"
    ],
    "poke_power": {
        "name": "Dozing",
        "effect": "Once during your turn (before your attack), if Snorlax is your Active Pokémon, you may remove 2 damage counters from Snorlax and Snorlax is now Asleep. This power can’t be used if Snorlax is affected by a Special Condition."
    },
    "poke_body": {
        "name": "Bedhead",
        "effect": "As long as Snorlax remains Asleep between turns, put 2 damage counters on 1 of the Defending Pokémon."
    },
    "weakness": {
        "type": [
            "Fighting"
        ],
        "value": "×2"
    },
    "resistance": {
        "type": [],
        "value": null
    },
    "retreat": 3
}