{
    "url": "https://pkmncards.com/card/croconaw-fusion-strike-fst-056/",
    "name": "Croconaw",
    "img": "https://pkmncards.com/wp-content/uploads/en_US-SWSH8-056-croconaw.jpg",
    "card_type": "Pokémon",
    "regulation": "E",
    "set_name": "FST",
    "set_img": null,
    "series": "Sword & Shield",
    "set_full_name": "Fusion Strike",
    "set_code": "SWSH8",
    "date": "Nov 12, 2021",
    "number": "056",
    "set_total": "264",
    "rarity": "Uncommon",
    "rarity_img": null,
    "author": [
        "Tomokazu Komiya"
    ],
    "flavor_text": "Once it bites down, it won’t let go until it loses its fangs. New fangs quickly grow into place.",
    "stage": "Stage 1",
    "hp": 100,
    "types": [
        "Water"
    ],
    "attacks": [
        {
            "cost": [
                "Water"
            ],
            "name": "Wave Splash",
            "damage": {
                "amount": 30,
                "suffix": ""
            },
            "effect": null
        },
        {
            "cost": [
                "Water",
                "Colorless",
                "Colorless"
            ],
            "name": "Surf",
            "damage": {
                "amount": 60,
                "suffix": ""
            },
            "effect": null
        }
    ],
    "weakness": {
        "type": [
            "Lightning"
        ],
        "value": "×2"
    },
    "resistance": {
        "type": [],
        "value": null
    },
    "retreat": 2,
    "evolve_from": "Totodile"
}