{
    "url": "https://pkmncards.com/card/adventurers-discovery-fusion-strike-fst-224/",
    "name": "Adventurer’s Discovery",
    "img": "https://pkmncards.com/wp-content/uploads/en_US-SWSH8-224-adventurers_discovery.jpg",
    "card_type": "Supporter",
    "regulation": "E",
    "set_name": "FST",
    "set_img": null,
    "series": "Sword & Shield",
    "set_full_name": "Fusion Strike",
    "set_code": "SWSH8",
    "date": "Nov 12, 2021",
    "number": "224",
    "set_total": "264",
    "rarity": "Uncommon",
    "rarity_img": null,
    "effect": "Search your deck for up to 3 Pokémon V, reveal them, and put them into your hand. Then, shuffle your deck.",
    "author": [
        "Taira Akitsu"
    ]
}