{
    "url": "https://pkmncards.com/card/celebi-shining-fates-shf-003/",
    "name": "Celebi",
    "img": "https://pkmncards.com/wp-content/uploads/en_US-SF-003-celebi.jpg",
    "card_type": "Pokémon",
    "regulation": "E",
    "set_name": "SHF",
    "set_img": null,
    "series": "Sword & Shield",
    "set_full_name": "Shining Fates",
    "set_code": "SWSH45SV",
    "date": "Feb 19, 2021",
    "number": "003",
    "set_total": "072",
    "rarity": "Rare",
    "rarity_img": null,
    "author": [
        "Yuu Nishida"
    ],
    "flavor_text": "It has the power to travel across time, but it is said to appear only in peaceful times.",
    "stage": "Basic",
    "hp": 70,
    "types": [
        "Grass"
    ],
    "abilities": [
        {
            "name": "Woodland Stroll",
            "effect": "Once during your turn, if this Pokémon is in the Active Spot, you may look at the top 6 cards of your deck, reveal an Energy card you find there, and put it into your hand. Shuffle the other cards back into your deck."
        }
    ],
    "attacks": [
        {
            "cost": [
                "Grass",
                "Colorless",
                "Colorless"
            ],
            "name": "Leaf Step",
            "damage": {
                "amount": 40,
                "suffix": ""
            },
            "effect": null
        }
    ],
    "weakness": {
        "type": [
            "Fire"
        ],
        "value": "×2"
    },
    "resistance": {
        "type": [],
        "value": null
    },
    "retreat": 1
}