{
    "url": "https://pkmncards.com/card/linoone-sandstorm-ss-44/",
    "name": "Linoone",
    "img": "https://pkmncards.com/wp-content/uploads/linoone-sandstorm-ss-44.jpg",
    "card_type": "Pokémon",
    "set_name": "SS",
    "series": "EX",
    "set_full_name": "Sandstorm",
    "set_code": "EX2",
    "date": "Sep 17, 2003",
    "number": "44",
    "set_total": "100",
    "rarity": "Uncommon",
    "author": [
        "Mitsuhiro Arita"
    ],
    "stage": "Stage 1",
    "hp": 70,
    "types": [
        "Colorless"
    ],
    "attacks": [
        {
            "cost": [
                "Colorless"
            ],
            "name": "Sniff Out",
            "damage": null,
            "effect": "Put any 1 card from your discard pile into your hand."
        },
        {
            "cost": [
                "Colorless",
                "Colorless"
            ],
            "name": "Fury Swipes",
            "damage": {
                "amount": 20,
                "suffix": "×"
            },
            "effect": "Flip 3 coins. This attack does 20 damage times the number of heads."
        }
    ],
    "weakness": {
        "type": [
            "Fighting"
        ],
        "value": "×2"
    },
    "resistance": {
        "type": [],
        "value": null
    },
    "retreat": 0,
    "evolve_from": "Zigzagoon"
}