{
    "url": "https://pkmncards.com/card/nidoran-female-triumphant-tm-69/",
    "name": "Nidoran Female",
    "img": "https://pkmncards.com/wp-content/uploads/en_US-HGSS4-069-nidoran.jpg",
    "card_type": "Pokémon",
    "set_name": "TM",
    "series": "HeartGold & SoulSilver",
    "set_full_name": "Triumphant",
    "set_code": "HGSS4",
    "date": "Nov 2, 2010",
    "number": "69",
    "set_total": "102",
    "rarity": "Common",
    "author": [
        "sui"
    ],
    "flavor_text": "Although not very combative, it will torment its foes with poison spikes if it is threatened in any way.",
    "stage": "Basic",
    "hp": 50,
    "types": [
        "Psychic"
    ],
    "attacks": [
        {
            "cost": [
                "Colorless"
            ],
            "name": "Friend Search",
            "damage": null,
            "effect": "Look at the top 5 cards of your deck, choose 1 Pokémon you find there, show it to your opponent, and put it into your hand. Shuffle the other cards back into your deck."
        },
        {
            "cost": [
                "Psychic",
                "Colorless"
            ],
            "name": "Double Kick",
            "damage": {
                "amount": 20,
                "suffix": "×"
            },
            "effect": "Flip 2 coins. This attack does 20 damage times the number of heads."
        }
    ],
    "weakness": {
        "type": [
            "Psychic"
        ],
        "value": "×2"
    },
    "resistance": {
        "type": [],
        "value": null
    },
    "retreat": 1
}