{
    "jp_id": 42389,
    "url": "https://www.pokemon-card.com/card-search/details.php/card/42389",
    "name": "\u30d2\u30b9\u30a4 \u30be\u30ed\u30a2\u30fc\u30afV",
    "img": "https://www.pokemon-card.com/assets/images/card_images/large/S12a/042389_P_HISUIZOROAKUV.jpg",
    "card_type": "Pok\u00e9mon",
    "tags": [
        "V"
    ],
    "set_name": "S12a",
    "set_img": "https://www.pokemon-card.com/assets/images/card/regulation_logo_1/S12a.gif",
    "number": "128",
    "set_total": "172",
    "rarity": "rare_rr",
    "rarity_img": "https://www.pokemon-card.com/assets/images/card/rarity/ic_rare_rr.gif",
    "author": [
        "aky CG Works"
    ],
    "stage": "\u305f\u306d",
    "hp": 210,
    "types": [
        "Colorless"
    ],
    "attacks": [
        {
            "cost": [
                "Void"
            ],
            "name": "\u3046\u3064\u308d\u304c\u3048\u308a",
            "damage": {
                "amount": 30,
                "suffix": ""
            },
            "effect": "\u306e\u305e\u3080\u306a\u3089\u3001\u3053\u306e\u30dd\u30b1\u30e2\u30f3\u3092\u30d9\u30f3\u30c1\u30dd\u30b1\u30e2\u30f3\u3068\u5165\u308c\u66ff\u3048\u308b\u3002"
        },
        {
            "cost": [
                "Colorless",
                "Colorless",
                "Colorless"
            ],
            "name": "\u30b7\u30e3\u30c9\u30fc\u30b5\u30a4\u30af\u30ed\u30f3",
            "damage": {
                "amount": 130,
                "suffix": ""
            },
            "effect": "\u3053\u306e\u30dd\u30b1\u30e2\u30f3\u306b\u3064\u3044\u3066\u3044\u308b\u30a8\u30cd\u30eb\u30ae\u30fc\u30921\u500b\u9078\u3073\u3001\u30d9\u30f3\u30c1\u30dd\u30b1\u30e2\u30f3\u306b\u3064\u3051\u66ff\u3048\u308b\u3002"
        }
    ],
    "rule_box": "\u30dd\u30b1\u30e2\u30f3V\u304c\u304d\u305c\u3064\u3057\u305f\u3068\u304d\u3001\u76f8\u624b\u306f\u30b5\u30a4\u30c9\u30922\u679a\u3068\u308b\u3002",
    "weakness": {
        "type": [
            "Fighting"
        ],
        "value": "\u00d72"
    },
    "resistance": {
        "type": [],
        "value": null
    },
    "retreat": 2,
    "sources": [
        {
            "name": "\u30cf\u30a4\u30af\u30e9\u30b9\u30d1\u30c3\u30af \u300cVSTAR\u30e6\u30cb\u30d0\u30fc\u30b9\u300d",
            "link": "https://www.pokemon-card.com/ex/s12a/"
        }
    ]
}