{
    "url": "https://pkmncards.com/card/scoop-up-legendary-collection-lc-104/",
    "name": "Scoop Up",
    "img": "https://pkmncards.com/wp-content/uploads/scoop-up-legendary-collection-lc-104.jpg",
    "card_type": "(Item)",
    "set_name": "LC",
    "series": "Other",
    "set_full_name": "Legendary Collection",
    "set_code": "LC",
    "date": "May 24, 2002",
    "number": "104",
    "set_total": "110",
    "rarity": "Rare",
    "effect": "Choose 1 of your Pokémon in play and return its Basic Pokémon card to your hand. (Discard all cards attached to that card.)",
    "author": [
        "Keiji Kinebuchi"
    ]
}