{
    "url": "https://pkmncards.com/card/dark-dragonite-legendary-collection-lc-5/",
    "name": "Dark Dragonite",
    "img": "https://pkmncards.com/wp-content/uploads/dark-dragonite-legendary-collection-lc-5.jpg",
    "card_type": "Pokémon",
    "set_name": "LC",
    "series": "Other",
    "set_full_name": "Legendary Collection",
    "set_code": "LC",
    "date": "May 24, 2002",
    "number": "5",
    "set_total": "110",
    "rarity": "Rare Holo",
    "author": [
        "Mitsuhiro Arita"
    ],
    "flavor_text": "Sometimes called “The God of Destruction.” Its wings are able to support it in spite of its massive weight.",
    "stage": "Stage 2",
    "level": "33",
    "hp": 70,
    "types": [
        "Colorless"
    ],
    "abilities": [
        {
            "name": "Summon Minions",
            "effect": " When you play Dark Dargonite from your hand, search your deck for up to 2 Basic Pokémon and put them onto your Bench. Shuffle your deck afterward."
        }
    ],
    "attacks": [
        {
            "cost": [
                "Colorless",
                "Colorless",
                "Colorless",
                "Colorless"
            ],
            "name": "Giant Tail",
            "damage": {
                "amount": 70,
                "suffix": ""
            },
            "effect": "Flip a coin. If tails, this attack does nothing."
        }
    ],
    "weakness": {
        "type": [],
        "value": null
    },
    "resistance": {
        "type": [
            "Fighting"
        ],
        "value": "-30"
    },
    "retreat": 2,
    "evolve_from": "Dark Dragonair"
}