{
    "url": "https://asia.pokemon-card.com/tw/card-search/detail/2267/",
    "name": "潛行惡能量",
    "img": "https://asia.pokemon-card.com/tw/card-img/tw00002267.png",
    "card_type": "特殊能量卡",
    "lang": "tc",
    "regulation": "D",
    "set_name": "SCD",
    "set_img": "https://asia.pokemon-card.com/tw/card-img/mark/S_mark_expantion_SCD_F_OL.png",
    "set_full_name": "V起始牌組 「強大」",
    "number": "158",
    "set_total": "159",
    "effect": "只要這張卡附於寶可夢身上，視為提供1個【惡】能量。附有這張卡的【惡】寶可夢【撤退】所需的能量全部消除。"
}