{
    "jp_id": 30289,
    "url": "https://www.pokemon-card.com/card-search/details.php/card/30289",
    "name": "ヌメラ",
    "img": "https://www.pokemon-card.com/assets/images/card_images/large/XY2/030289_P_NUMERA.jpg",
    "card_type": "Pokémon",
    "set_name": "XY2",
    "set_img": "https://www.pokemon-card.com/assets/images/card/regulation_logo_1/XY2.gif",
    "number": "058",
    "set_total": "080",
    "rarity": "rare_c_c",
    "rarity_img": "https://www.pokemon-card.com/assets/images/card/rarity/ic_rare_c_c.gif",
    "author": [
        "5ban Graphics"
    ],
    "pokedex_number": 704,
    "pokemon_category": "なんたいポケモン",
    "height": "0.3 m",
    "weight": "2.8 kg",
    "flavor_text": "一番 弱い ドラゴンポケモン。 ヌメヌメの 体が 乾かないよう ジメジメした 日陰で 暮らす。",
    "stage": "たね",
    "hp": 50,
    "types": [
        "Dragon"
    ],
    "attacks": [
        {
            "cost": [
                "Colorless"
            ],
            "name": "ぬめぬめ",
            "damage": null,
            "effect": "このポケモンのHPを「10」回復する。"
        },
        {
            "cost": [
                "Water",
                "Fairy"
            ],
            "name": "たいあたり",
            "damage": {
                "amount": 20,
                "suffix": ""
            },
            "effect": ""
        }
    ],
    "weakness": {
        "type": [
            "Fairy"
        ],
        "value": "×2"
    },
    "resistance": {
        "type": [],
        "value": null
    },
    "retreat": 2,
    "sources": [
        {
            "name": "ポケモンカードゲームXY 拡張パック「ワイルドブレイズ」",
            "link": "https://www.pokemon-card.com/products/xy/xy2.html"
        }
    ]
}