{
    "url": "https://pkmncards.com/card/timburr-battle-styles-bst-073/",
    "name": "Timburr",
    "img": "https://pkmncards.com/wp-content/uploads/en_US-SWSH5-073-timburr.jpg",
    "card_type": "Pokémon",
    "regulation": "E",
    "set_name": "BST",
    "set_img": null,
    "series": "Sword & Shield",
    "set_full_name": "Battle Styles",
    "set_code": "SWSH5",
    "date": "Mar 19, 2021",
    "number": "073",
    "set_total": "163",
    "rarity": "Common",
    "rarity_img": null,
    "author": [
        "Mina Nakai"
    ],
    "flavor_text": "Timburr that have started carrying logs that are about three times their size are nearly ready to evolve.",
    "stage": "Basic",
    "hp": 80,
    "types": [
        "Fighting"
    ],
    "attacks": [
        {
            "cost": [
                "Colorless",
                "Colorless"
            ],
            "name": "Pound",
            "damage": {
                "amount": 20,
                "suffix": ""
            },
            "effect": null
        }
    ],
    "weakness": {
        "type": [
            "Psychic"
        ],
        "value": "×2"
    },
    "resistance": {
        "type": [],
        "value": null
    },
    "retreat": 2
}