{
    "url": "https://pkmncards.com/card/ducklett-cosmic-eclipse-cec-59/",
    "name": "Ducklett",
    "img": "https://pkmncards.com/wp-content/uploads/en_US-SM12-059-ducklett.jpg",
    "card_type": "Pokémon",
    "set_name": "CEC",
    "series": "Sun & Moon",
    "set_full_name": "Cosmic Eclipse",
    "set_code": "SM12",
    "date": "Nov 1, 2019",
    "number": "59",
    "set_total": "236",
    "rarity": "Common",
    "author": [
        "Yumi"
    ],
    "flavor_text": "When attacked, it uses its feathers to splash water, escaping under cover of the spray.",
    "stage": "Basic",
    "hp": 60,
    "types": [
        "Water"
    ],
    "attacks": [
        {
            "cost": [
                "Colorless",
                "Colorless"
            ],
            "name": "Aerial Ace",
            "damage": {
                "amount": 10,
                "suffix": "+"
            },
            "effect": "Flip a coin. If heads, this attack does 30 more damage."
        }
    ],
    "weakness": {
        "type": [
            "Lightning"
        ],
        "value": "×2"
    },
    "resistance": {
        "type": [
            "Fighting"
        ],
        "value": "-20"
    },
    "retreat": 1
}