{
    "jp_id": 43682,
    "url": "https://www.pokemon-card.com/card-search/details.php/card/43682",
    "name": "\u30a4\u30ad\u30ea\u30f3\u30b3ex",
    "img": "https://www.pokemon-card.com/assets/images/card_images/large/SV2P/043682_P_IKIRINKOEX.jpg",
    "card_type": "Pok\u00e9mon",
    "tags": [
        "ex"
    ],
    "set_name": "SV2P",
    "set_img": "https://www.pokemon-card.com/assets/images/card/regulation_logo_1/SV2P.gif",
    "number": "089",
    "set_total": "071",
    "rarity": "rare_sr_c",
    "rarity_img": "https://www.pokemon-card.com/assets/images/card/rarity/ic_rare_sr_c.gif",
    "author": [
        "PLANETA Mochizuki"
    ],
    "stage": "\u305f\u306d",
    "hp": 160,
    "types": [
        "Colorless"
    ],
    "abilities": [
        {
            "name": "\u30a4\u30ad\u30ea\u30c6\u30a4\u30af",
            "effect": "\u6700\u521d\u306e\u81ea\u5206\u306e\u756a\u306b\u3060\u30511\u56de\u4f7f\u3048\u308b\u3002\u81ea\u5206\u306e\u624b\u672d\u3092\u3059\u3079\u3066\u30c8\u30e9\u30c3\u30b7\u30e5\u3057\u3001\u5c71\u672d\u30926\u679a\u5f15\u304f\u3002\u3053\u306e\u756a\u3001\u3059\u3067\u306b\u5225\u306e\u300c\u30a4\u30ad\u30ea\u30c6\u30a4\u30af\u300d\u3092\u4f7f\u3063\u3066\u3044\u305f\u306a\u3089\u3001\u3053\u306e\u7279\u6027\u306f\u4f7f\u3048\u306a\u3044\u3002"
        }
    ],
    "attacks": [
        {
            "cost": [
                "Colorless"
            ],
            "name": "\u304d\u3042\u3044\u3092\u3044\u308c\u308b",
            "damage": {
                "amount": 20,
                "suffix": ""
            },
            "effect": "\u81ea\u5206\u306e\u30c8\u30e9\u30c3\u30b7\u30e5\u304b\u3089\u57fa\u672c\u30a8\u30cd\u30eb\u30ae\u30fc\u30922\u679a\u307e\u3067\u9078\u3073\u3001\u30d9\u30f3\u30c1\u30dd\u30b1\u30e2\u30f31\u5339\u306b\u3064\u3051\u308b\u3002"
        }
    ],
    "rule_box": "\u30dd\u30b1\u30e2\u30f3ex\u304c\u304d\u305c\u3064\u3057\u305f\u3068\u304d\u3001\u76f8\u624b\u306f\u30b5\u30a4\u30c9\u30922\u679a\u3068\u308b\u3002",
    "weakness": {
        "type": [
            "Electric"
        ],
        "value": "\u00d72"
    },
    "resistance": {
        "type": [
            "Fighting"
        ],
        "value": "\uff0d30"
    },
    "retreat": 1,
    "sources": [
        {
            "name": "\u62e1\u5f35\u30d1\u30c3\u30af\u300c\u30b9\u30ce\u30fc\u30cf\u30b6\u30fc\u30c9\u300d",
            "link": "https://www.pokemon-card.com/products/sv/sv2.html"
        }
    ]
}