{
    "url": "https://asia.pokemon-card.com/tw/card-search/detail/4129/",
    "name": "阿羅拉 穿山王",
    "img": "https://asia.pokemon-card.com/tw/card-img/tw00004129.png",
    "card_type": "Pokémon",
    "lang": "tc",
    "regulation": "A",
    "set_name": "AC1b",
    "set_img": "https://asia.pokemon-card.com/tw/card-img/mark/SM_expantion_ac1b.png",
    "set_full_name": "擴充包「眾星雲集組合篇」SET B",
    "number": "003",
    "set_total": "158",
    "author": [
        "TOKIYA"
    ],
    "pokedex_number": "28",
    "pokemon_category": "鼠寶可夢",
    "height": "1.2",
    "weight": "55",
    "flavor_text": "從火山爆發逃難的最後，在雪山棲息定居下來。會濺起雪花在雪原上奔馳。",
    "stage": "1階進化",
    "hp": "110",
    "types": [
        "Water"
    ],
    "abilities": [
        {
            "name": "撥雪",
            "effect": "在自己的回合時，可使用1次。從自己的牌庫抽出1張。"
        }
    ],
    "attacks": [
        {
            "cost": [
                "Water",
                "Colorless",
                "Colorless"
            ],
            "name": "粉碎迴轉",
            "damage": "50",
            "effect": "將這隻寶可夢與備戰寶可夢互換。"
        }
    ],
    "weakness": {
        "type": [
            "Metal"
        ],
        "value": "×2"
    },
    "resistance": {
        "type": [],
        "value": null
    },
    "retreat": 2,
    "evolve_from": [
        "阿羅拉 穿山鼠"
    ]
}