{
    "url": "https://asia.pokemon-card.com/tw/card-search/detail/3355/",
    "name": "始祖小鳥",
    "img": "https://asia.pokemon-card.com/tw/card-img/tw00003355.png",
    "card_type": "Pokémon",
    "lang": "tc",
    "regulation": "C",
    "set_name": "AS6b",
    "set_img": "https://asia.pokemon-card.com/tw/card-img/mark/SM_expantion_mark_as6bOUT.png",
    "set_full_name": "擴充包「傳說交鋒」SET B",
    "number": "114",
    "set_total": "194",
    "author": [
        "313"
    ],
    "pokedex_number": "566",
    "pokemon_category": "遠古鳥寶可夢",
    "height": "0.5",
    "weight": "9.5",
    "flavor_text": "是所有鳥寶可夢的祖先。始祖小鳥本身還不會飛，而是在樹上跳著移動。",
    "stage": "1階進化",
    "hp": "80",
    "types": [
        "Fighting"
    ],
    "attacks": [
        {
            "cost": [
                "Colorless"
            ],
            "name": "蠻幹",
            "damage": "20+",
            "effect": "擲2次硬幣，增加正面出現的次數×20點傷害。"
        }
    ],
    "weakness": {
        "type": [
            "Lightning"
        ],
        "value": "×2"
    },
    "resistance": {
        "type": [
            "Fighting"
        ],
        "value": "-20"
    },
    "retreat": 1
}