{
    "url": "https://asia.pokemon-card.com/tw/card-search/detail/5664/",
    "name": "敲音猴",
    "img": "https://asia.pokemon-card.com/tw/card-img/tw00005664.png",
    "card_type": "Pokémon",
    "lang": "tc",
    "regulation": "E",
    "set_name": "SI",
    "set_img": "https://asia.pokemon-card.com/tw/card-img/mark/S_mark_expantion_SI_F.png",
    "set_full_name": "初階牌組100",
    "number": "035",
    "set_total": "414",
    "author": [
        "kodama"
    ],
    "pokedex_number": "810",
    "pokemon_category": "小猴寶可夢",
    "height": "0.3",
    "weight": "5",
    "flavor_text": "會用木棒連續擊打來攻擊。在以飛快的速度擊打的同時，情緒也會變得越來越高漲。",
    "stage": "基礎",
    "hp": "60",
    "types": [
        "Grass"
    ],
    "attacks": [
        {
            "cost": [
                "Grass",
                "Colorless"
            ],
            "name": "二連敲",
            "damage": "30×",
            "effect": "擲2次硬幣，造成正面出現的次數×30點傷害。"
        },
        {
            "cost": [],
            "name": "",
            "damage": "",
            "effect": ""
        }
    ],
    "weakness": {
        "type": [
            "Fire"
        ],
        "value": "×2"
    },
    "resistance": {
        "type": [],
        "value": null
    },
    "retreat": 1
}