{
    "url": "https://pkmncards.com/card/regigigas-crimson-invasion-cin-84a/",
    "name": "Regigigas",
    "img": "https://pkmncards.com/wp-content/uploads/en_US-SM4-84a-regigigas-yaa.jpg",
    "card_type": "Pokémon",
    "set_name": "CIN",
    "series": "Sun & Moon",
    "set_full_name": "Crimson Invasion",
    "set_code": "SM4",
    "date": "May 4, 2018",
    "number": "84a",
    "set_total": "111",
    "rarity": "Rare Holo",
    "author": [
        "Hasuno"
    ],
    "flavor_text": "It is said to have made Pokémon that look like itself from a special ice mountain, rocks, and magma.",
    "stage": "Basic",
    "hp": 180,
    "types": [
        "Colorless"
    ],
    "abilities": [
        {
            "name": "Seal of Antiquity",
            "effect": "This Pokémon can’t attack unless Regirock, Regice, and Registeel are on your Bench."
        }
    ],
    "attacks": [
        {
            "cost": [
                "Colorless",
                "Colorless",
                "Colorless",
                "Colorless",
                "Colorless"
            ],
            "name": "Giant Stomp",
            "damage": {
                "amount": 160,
                "suffix": ""
            },
            "effect": "Discard any Stadium card in play."
        }
    ],
    "weakness": {
        "type": [
            "Fighting"
        ],
        "value": "×2"
    },
    "resistance": {
        "type": [],
        "value": null
    },
    "retreat": 4
}