{
    "url": "https://pkmncards.com/card/pelipper-celestial-storm-ces-112/",
    "name": "Pelipper",
    "img": "https://pkmncards.com/wp-content/uploads/en_US-SM7-112-pelipper.jpg",
    "card_type": "Pokémon",
    "set_name": "CES",
    "series": "Sun & Moon",
    "set_full_name": "Celestial Storm",
    "set_code": "SM7",
    "date": "Aug 3, 2018",
    "number": "112",
    "set_total": "168",
    "rarity": "Uncommon",
    "author": [
        "Shigenori Negishi"
    ],
    "flavor_text": "Gathering food is the work of young males. They store food in their capacious beaks and carry it back to others waiting in the nest.",
    "stage": "Stage 1",
    "hp": 120,
    "types": [
        "Colorless"
    ],
    "attacks": [
        {
            "cost": [
                "Colorless"
            ],
            "name": "Firefighting",
            "damage": {
                "amount": 30,
                "suffix": ""
            },
            "effect": "Discard a {R} Energy from your opponent’s Active Pokémon."
        },
        {
            "cost": [
                "Colorless",
                "Colorless",
                "Colorless"
            ],
            "name": "Water Pulse",
            "damage": {
                "amount": 80,
                "suffix": ""
            },
            "effect": "Your opponent’s Active Pokémon is now Asleep."
        }
    ],
    "weakness": {
        "type": [
            "Lightning"
        ],
        "value": "×2"
    },
    "resistance": {
        "type": [
            "Fighting"
        ],
        "value": "-20"
    },
    "retreat": 2,
    "evolve_from": "Wingull"
}