{
    "url": "https://asia.pokemon-card.com/tw/card-search/detail/9901/",
    "name": "老翁龍",
    "img": "https://asia.pokemon-card.com/tw/card-img/tw00009901.png",
    "card_type": "Pokémon",
    "lang": "tc",
    "regulation": "H",
    "set_name": "EXpansion",
    "set_img": "https://asia.pokemon-card.com/tw/card-img/mark/expansion_mark_SV5M.png",
    "set_full_name": "擴充包「異度審判」",
    "number": "060",
    "set_total": "071",
    "author": [
        "Toshinao Aoki"
    ],
    "pokedex_number": "780",
    "pokemon_category": "悠遊寶可夢",
    "height": "3.0m",
    "weight": "185.0kg",
    "flavor_text": "住在海拔超過３０００公尺的山上。偶爾也會來到城鎮，與住在那裡的孩子們一起玩耍。",
    "stage": "基礎",
    "hp": "120",
    "types": [
        "Colorless"
    ],
    "attacks": [
        {
            "cost": [
                "Colorless"
            ],
            "name": "重摑",
            "damage": "20",
            "effect": ""
        },
        {
            "cost": [
                "Colorless",
                "Colorless",
                "Colorless"
            ],
            "name": "盛怒炮",
            "damage": "100+",
            "effect": "若自己的所有備戰寶可夢身上都放置有傷害指示物，則增加120點傷害。"
        }
    ],
    "weakness": {
        "type": [
            "Fighting"
        ],
        "value": "×2"
    },
    "resistance": {
        "type": [],
        "value": null
    },
    "retreat": 2
}