{
    "url": "https://asia.pokemon-card.com/tw/card-search/detail/6355/",
    "name": "圈圈熊",
    "img": "https://asia.pokemon-card.com/tw/card-img/tw00006355.png",
    "card_type": "Pokémon",
    "lang": "tc",
    "regulation": "F",
    "set_name": "S10P",
    "set_img": "https://asia.pokemon-card.com/tw/card-img/mark/S10P_F.png",
    "set_full_name": "擴充包「空間魔術師」",
    "number": "056",
    "set_total": "067",
    "author": [
        "Teeziro"
    ],
    "pokedex_number": "217",
    "pokemon_category": "冬眠寶可夢",
    "height": "1.8",
    "weight": "125.8",
    "flavor_text": "在洗翠大地被嚴寒籠罩的季節裡，徘徊於山野之中尋找愛吃的樹果。空腹帶來的焦躁使牠變得極為凶暴。",
    "stage": "1階進化",
    "hp": "130",
    "types": [
        "Colorless"
    ],
    "attacks": [
        {
            "cost": [
                "Colorless"
            ],
            "name": "連續巴掌",
            "damage": "40×",
            "effect": "擲硬幣直到出現反面，造成正面出現的次數×40點傷害。"
        },
        {
            "cost": [
                "Colorless",
                "Colorless",
                "Colorless"
            ],
            "name": "怪力",
            "damage": "100",
            "effect": ""
        }
    ],
    "weakness": {
        "type": [
            "Fighting"
        ],
        "value": "×2"
    },
    "resistance": {
        "type": [],
        "value": null
    },
    "retreat": 3,
    "evolve_from": [
        "熊寶寶"
    ]
}