{
    "url": "https://www.pokemon-card.com/card-search/details.php/card/45865",
    "name": "ゼイユ",
    "img": "https://www.pokemon-card.com/assets/images/card_images/large/SV6/045865_T_ZEIYU.jpg",
    "card_type": "サポート",
    "jp_id": 45865,
    "set_name": "SV6",
    "set_img": "https://www.pokemon-card.com/assets/images/card/regulation_logo_1/SV6.gif",
    "number": "123",
    "set_total": "101",
    "rarity": "rare_sr_c",
    "rarity_img": "https://www.pokemon-card.com/assets/images/card/rarity/ic_rare_sr_c.gif",
    "effect": "このカードは、先攻プレイヤーの最初の番でも使える。\n自分の手札をすべてトラッシュし、山札を5枚引く。",
    "author": [
        "kantaro"
    ],
    "sources": [
        {
            "name": "拡張パック「変幻の仮面」",
            "link": "https://www.pokemon-card.com/ex/sv6/"
        }
    ]
}