{
    "url": "https://asia.pokemon-card.com/tw/card-search/detail/3449/",
    "name": "火恐龍",
    "img": "https://asia.pokemon-card.com/tw/card-img/tw00003449.png",
    "card_type": "Pokémon",
    "lang": "tc",
    "regulation": "C",
    "set_name": "AS5D",
    "set_img": "https://asia.pokemon-card.com/tw/card-img/mark/SM_expantion_mark_as5DOUT.png",
    "set_full_name": "G超起始牌組「雙倍爆擊」",
    "number": "014",
    "set_total": "169",
    "author": [
        "Ayaka Yoshida"
    ],
    "pokedex_number": "5",
    "pokemon_category": "火焰寶可夢",
    "height": "1.1",
    "weight": "19",
    "flavor_text": "會用銳利的爪子無情地打倒對手。遇到強敵時會興奮起來，尾巴上會燃起藍白色的火焰。",
    "stage": "1階進化",
    "hp": "90",
    "types": [
        "Fire"
    ],
    "attacks": [
        {
            "cost": [
                "Fire",
                "Fire"
            ],
            "name": "火焰牙",
            "damage": "30",
            "effect": "將對手的戰鬥寶可夢【灼傷】。"
        }
    ],
    "weakness": {
        "type": [
            "Water"
        ],
        "value": "×2"
    },
    "resistance": {
        "type": [],
        "value": null
    },
    "retreat": 2,
    "evolve_from": [
        "小火龍"
    ]
}